{"target_version":"0.34b7","vehicle_attributes":{"headlights":{"headlight_color":-1,"headlights_color":255,"headlights_type":false},"paint":{"livery2_legacy":-1,"primary":{"paint_type":131,"vehicle_standard_color":0,"custom_color":{"g":0,"r":0,"b":0},"color":132,"is_custom":true,"pearlescent_color":217},"livery_legacy":-1,"vehicle_custom_color":{"g":8,"r":8,"b":8},"interior_color":0,"dashboard_color":0,"fade":0.568627,"extra_colors":{"wheel":156,"pearlescent":10},"dirt_level":7.096572,"secondary":{"paint_type":131,"vehicle_standard_color":0,"custom_color":{"g":73,"r":69,"b":0},"color":132,"is_custom":true},"color_combo":-1,"livery":-1},"options":{"engine_running":true,"window_tint":-1,"radio_loud":false,"siren":false,"search_light":false,"license_plate_text":"82JRS561","license_plate_type":4,"bulletproof_tires":false,"emergency_lights":false},"doors":{"broken":{},"open":{"backleft":false,"hood":false,"frontright":false,"trunk":false,"trunk2":false,"backright":false,"frontleft":false}},"extras":{"_1":true,"_5":true,"_4":true,"_3":true,"_2":true,"_6":true,"_7":true,"_8":true,"_9":true},"mods":{"_0":-1,"_32":-1,"_11":-1,"_40":-1,"_17":true,"_13":-1,"_33":-1,"_34":-1,"_41":-1,"_18":false,"_15":-1,"_39":-1,"_42":-1,"_19":false,"_6":-1,"_16":-1,"_8":-1,"_14":-1,"_10":-1,"_1":-1,"_21":false,"_22":false,"_5":-1,"_29":-1,"_3":-1,"_25":-1,"_27":-1,"_30":-1,"_23":-1,"_20":false,"_2":-1,"_12":-1,"_26":-1,"_35":-1,"_31":-1,"_48":-1,"_28":-1,"_44":-1,"_36":-1,"_24":-1,"_37":-1,"_38":-1,"_49":-1,"_4":-1,"_45":-1,"_46":-1,"_47":-1,"_7":-1,"_43":-1,"_9":-1},"wheels":{"wheel_type":0,"tire_smoke_color":{"g":255,"r":255,"b":255},"tires_burst":{}},"neon":{"lights":{"right":false,"back":false,"front":false,"left":false},"color":{}},"windows":{"broken":{"rearright":false,"midright":false,"front":false,"frontright":false,"rearleft":false,"rear":false,"midleft":false,"frontleft":false},"rolled_down":{}}},"blip_color":2,"children":[{"target_version":"0.34b7","world_rotation":{"z":97.887436,"y":0.535431,"x":-85.639465},"blip_color":2,"children":[{"target_version":"0.34b7","world_rotation":{"z":-82.649551,"y":89.959152,"x":-4.360395},"blip_color":2,"children":[{"target_version":"0.34b7","world_rotation":{"z":-82.649551,"y":-90.040825,"x":-4.360396},"blip_color":2,"children":[{"target_version":"0.34b7","world_rotation":{"z":-82.649551,"y":-90.040825,"x":-4.360396},"blip_color":2,"children":{},"type":"OBJECT","offset":{"z":-2.0,"y":0.0,"x":0},"rotation_order":2,"options":{"object_tint":0,"is_explosion_proof":false,"lod_distance":16960,"has_collision":true,"is_light_on":true,"is_attached":true,"buoyancy":0.0,"is_bullet_proof":false,"is_mission_entity":true,"use_soft_pinning":true,"is_dynamic":true,"is_fire_proof":false,"gravity":0.0,"is_invincible":true,"alpha":255,"bone_index":0,"weight":0.0,"is_visible":true,"is_networked":true,"is_melee_proof":false,"is_driver_visible":true,"has_gravity":true},"name":"425311731","num_bones":0,"rotation":{"z":0,"y":0,"x":0},"hash":"425311731","position":{"z":33.649338,"y":-1654.943604,"x":-182.098709},"blip_icon":1,"model":"prop_bush_ivy_02_pot"},{"target_version":"0.34b7","world_rotation":{"z":97.350426,"y":-89.95916,"x":4.360396},"blip_color":2,"children":{},"type":"OBJECT","offset":{"z":6.4,"y":3.6,"x":0.0},"rotation_order":2,"options":{"object_tint":0,"is_explosion_proof":false,"lod_distance":16960,"has_collision":true,"is_light_on":true,"is_attached":true,"buoyancy":0.0,"is_bullet_proof":false,"is_mission_entity":true,"use_soft_pinning":true,"is_dynamic":true,"is_fire_proof":false,"gravity":0.0,"is_invincible":true,"alpha":255,"bone_index":0,"weight":0.0,"is_visible":true,"is_networked":true,"is_melee_proof":false,"is_driver_visible":true,"has_gravity":true},"name":"425311731","num_bones":0,"rotation":{"z":0,"y":0,"x":-180},"hash":"425311731","position":{"z":33.369659,"y":-1646.153442,"x":-179.613754},"blip_icon":1,"model":"prop_bush_ivy_02_pot"},{"target_version":"0.34b7","world_rotation":{"z":-82.649551,"y":-90.040825,"x":-4.360396},"blip_color":2,"children":[{"target_version":"0.34b7","world_rotation":{"z":-82.649551,"y":89.959152,"x":-4.360395},"blip_color":2,"children":[{"target_version":"0.34b7","world_rotation":{"z":-82.112686,"y":-0.535286,"x":85.639549},"blip_color":2,"children":[{"target_version":"0.34b7","world_rotation":{"z":-82.112686,"y":-0.535286,"x":85.639549},"blip_color":2,"children":[{"target_version":"0.34b7","world_rotation":{"z":7.353574,"y":-85.639595,"x":-0.040702},"blip_color":2,"children":[{"target_version":"0.34b7","world_rotation":{"z":7.353574,"y":94.360397,"x":-0.040702},"blip_color":2,"children":{},"type":"OBJECT","offset":{"z":2.0,"y":0.0,"x":-0.1},"rotation_order":2,"options":{"object_tint":0,"is_explosion_proof":false,"lod_distance":16960,"has_collision":true,"is_light_on":true,"is_attached":true,"buoyancy":0.0,"is_bullet_proof":false,"is_mission_entity":true,"use_soft_pinning":true,"is_dynamic":true,"is_fire_proof":false,"gravity":0.0,"is_invincible":true,"alpha":255,"bone_index":0,"weight":0.0,"is_visible":true,"is_networked":true,"is_melee_proof":false,"is_driver_visible":true,"has_gravity":true},"name":"425311731","num_bones":0,"rotation":{"z":0,"y":180,"x":0},"hash":"425311731","position":{"z":33.580624,"y":-1654.432129,"x":-181.259888},"blip_icon":1,"model":"prop_bush_ivy_02_pot"},{"target_version":"0.34b7","world_rotation":{"z":-172.646408,"y":85.639595,"x":0.040707},"blip_color":2,"children":[{"target_version":"0.34b7","world_rotation":{"z":-172.646408,"y":-94.360397,"x":0.040707},"blip_color":2,"children":[{"target_version":"0.34b7","world_rotation":{"z":-172.646454,"y":-4.360398,"x":0.040699},"blip_color":2,"children":[{"target_version":"0.34b7","world_rotation":{"z":-172.646454,"y":-4.360398,"x":0.040699},"blip_color":2,"children":{},"type":"OBJECT","offset":{"z":-0.5,"y":1.6,"x":-0.7},"rotation_order":2,"options":{"object_tint":0,"is_explosion_proof":false,"lod_distance":16960,"has_collision":true,"is_light_on":true,"is_attached":true,"buoyancy":0.0,"is_bullet_proof":false,"is_mission_entity":true,"use_soft_pinning":true,"is_dynamic":true,"is_fire_proof":false,"gravity":0.0,"is_invincible":true,"alpha":255,"bone_index":0,"weight":0.0,"is_visible":true,"is_networked":true,"is_melee_proof":false,"is_driver_visible":true,"has_gravity":true},"name":"1165271193","num_bones":0,"rotation":{"z":0,"y":0,"x":0},"hash":"1165271193","position":{"z":34.148636,"y":-1653.216309,"x":-179.654007},"blip_icon":1,"model":"prop_bush_med_06"}],"type":"OBJECT","offset":{"z":-0.8,"y":5.0,"x":1.2},"rotation_order":2,"options":{"object_tint":0,"is_explosion_proof":false,"lod_distance":16960,"has_collision":true,"is_light_on":true,"is_attached":true,"buoyancy":0.0,"is_bullet_proof":false,"is_mission_entity":true,"use_soft_pinning":true,"is_dynamic":true,"is_fire_proof":false,"gravity":0.0,"is_invincible":true,"alpha":255,"bone_index":0,"weight":0.0,"is_visible":true,"is_networked":true,"is_melee_proof":false,"is_driver_visible":true,"has_gravity":true},"name":"-1705943745","num_bones":0,"rotation":{"z":0,"y":90,"x":0},"hash":"-1705943745","position":{"z":34.699272,"y":-1651.713501,"x":-180.513367},"blip_icon":1,"model":"prop_bush_lrg_01e_cr2"}],"type":"OBJECT","offset":{"z":-1.6,"y":0.0,"x":0.0},"rotation_order":2,"options":{"object_tint":0,"is_explosion_proof":false,"lod_distance":16960,"has_collision":true,"is_light_on":true,"is_attached":true,"buoyancy":0.0,"is_bullet_proof":false,"is_mission_entity":true,"use_soft_pinning":true,"is_dynamic":true,"is_fire_proof":false,"gravity":0.0,"is_invincible":true,"alpha":255,"bone_index":0,"weight":0.0,"is_visible":true,"is_networked":true,"is_melee_proof":false,"is_driver_visible":true,"has_gravity":true},"name":"-2145301823","num_bones":0,"rotation":{"z":0,"y":-180,"x":0},"hash":"-2145301823","position":{"z":33.43837,"y":-1646.665039,"x":-180.452576},"blip_icon":1,"model":"prop_bush_ivy_02_1m"}],"type":"OBJECT","offset":{"z":1.8,"y":7.6,"x":-0.1},"rotation_order":2,"options":{"object_tint":0,"is_explosion_proof":false,"lod_distance":16960,"has_collision":true,"is_light_on":true,"is_attached":true,"buoyancy":0.0,"is_bullet_proof":false,"is_mission_entity":true,"use_soft_pinning":true,"is_dynamic":true,"is_fire_proof":false,"gravity":0.0,"is_invincible":true,"alpha":255,"bone_index":0,"weight":0.0,"is_visible":true,"is_networked":true,"is_melee_proof":false,"is_driver_visible":true,"has_gravity":true},"name":"-2145301823","num_bones":0,"rotation":{"z":180,"y":0,"x":0},"hash":"-2145301823","position":{"z":33.560017,"y":-1646.869141,"x":-182.034836},"blip_icon":1,"model":"prop_bush_ivy_02_1m"}],"type":"OBJECT","offset":{"z":0.1,"y":-0.5,"x":6.5},"rotation_order":2,"options":{"object_tint":0,"is_explosion_proof":false,"lod_distance":16960,"has_collision":true,"is_light_on":true,"is_attached":true,"buoyancy":0.0,"is_bullet_proof":false,"is_mission_entity":true,"use_soft_pinning":true,"is_dynamic":true,"is_fire_proof":false,"gravity":0.0,"is_invincible":true,"alpha":255,"bone_index":0,"weight":0.0,"is_visible":true,"is_networked":true,"is_melee_proof":false,"is_driver_visible":true,"has_gravity":true},"name":"425311731","num_bones":0,"rotation":{"z":90,"y":0,"x":0},"hash":"425311731","position":{"z":33.528275,"y":-1654.175903,"x":-179.274536},"blip_icon":1,"model":"prop_bush_ivy_02_pot"}],"type":"OBJECT","offset":{"z":-1.8,"y":0.0,"x":0.0},"rotation_order":2,"options":{"object_tint":0,"is_explosion_proof":false,"lod_distance":16960,"has_collision":true,"is_light_on":true,"is_attached":true,"buoyancy":0.0,"is_bullet_proof":false,"is_mission_entity":true,"use_soft_pinning":true,"is_dynamic":true,"is_fire_proof":false,"gravity":0.0,"is_invincible":true,"alpha":255,"bone_index":0,"weight":0.0,"is_visible":true,"is_networked":true,"is_melee_proof":false,"is_driver_visible":true,"has_gravity":true},"name":"-467587443","num_bones":0,"rotation":{"z":0,"y":0,"x":0},"hash":"-467587443","position":{"z":34.014606,"y":-1647.711426,"x":-179.969925},"blip_icon":1,"model":"prop_bush_ivy_02_l"}],"type":"OBJECT","offset":{"z":-3.6,"y":-2.7,"x":-0.6},"rotation_order":2,"options":{"object_tint":0,"is_explosion_proof":false,"lod_distance":16960,"has_collision":true,"is_light_on":true,"is_attached":true,"buoyancy":0.0,"is_bullet_proof":false,"is_mission_entity":true,"use_soft_pinning":true,"is_dynamic":true,"is_fire_proof":false,"gravity":0.0,"is_invincible":true,"alpha":255,"bone_index":0,"weight":0.0,"is_visible":true,"is_networked":true,"is_melee_proof":false,"is_driver_visible":true,"has_gravity":true},"name":"-467587443","num_bones":0,"rotation":{"z":90,"y":-90,"x":0},"hash":"-467587443","position":{"z":34.151459,"y":-1647.94104,"x":-181.749969},"blip_icon":1,"model":"prop_bush_ivy_02_l"}],"type":"OBJECT","offset":{"z":1.3,"y":0.0,"x":0.0},"rotation_order":2,"options":{"object_tint":0,"is_explosion_proof":false,"lod_distance":16960,"has_collision":true,"is_light_on":true,"is_attached":true,"buoyancy":0.0,"is_bullet_proof":false,"is_mission_entity":true,"use_soft_pinning":true,"is_dynamic":true,"is_fire_proof":false,"gravity":0.0,"is_invincible":true,"alpha":255,"bone_index":0,"weight":0.0,"is_visible":true,"is_networked":true,"is_melee_proof":false,"is_driver_visible":true,"has_gravity":true},"name":"425311731","num_bones":0,"rotation":{"z":0,"y":-180,"x":0},"hash":"425311731","position":{"z":33.350475,"y":-1651.173218,"x":-178.664322},"blip_icon":1,"model":"prop_bush_ivy_02_pot"}],"type":"OBJECT","offset":{"z":0.0,"y":3.9,"x":0},"rotation_order":2,"options":{"object_tint":0,"is_explosion_proof":false,"lod_distance":16960,"has_collision":true,"is_light_on":true,"is_attached":true,"buoyancy":0.0,"is_bullet_proof":false,"is_mission_entity":true,"use_soft_pinning":true,"is_dynamic":true,"is_fire_proof":false,"gravity":0.0,"is_invincible":true,"alpha":255,"bone_index":0,"weight":0.0,"is_visible":true,"is_networked":true,"is_melee_proof":false,"is_driver_visible":true,"has_gravity":true},"name":"425311731","num_bones":0,"rotation":{"z":0,"y":0,"x":0},"hash":"425311731","position":{"z":33.351398,"y":-1652.462524,"x":-178.49794},"blip_icon":1,"model":"prop_bush_ivy_02_pot"}],"type":"OBJECT","offset":{"z":6.1,"y":0.0,"x":0.0},"rotation_order":2,"options":{"object_tint":0,"is_explosion_proof":false,"lod_distance":16960,"has_collision":true,"is_light_on":true,"is_attached":true,"buoyancy":0.0,"is_bullet_proof":false,"is_mission_entity":true,"use_soft_pinning":true,"is_dynamic":true,"is_fire_proof":false,"gravity":0.0,"is_invincible":true,"alpha":255,"bone_index":0,"weight":0.0,"is_visible":true,"is_networked":true,"is_melee_proof":false,"is_driver_visible":true,"has_gravity":true},"name":"425311731","num_bones":0,"rotation":{"z":0,"y":180,"x":0},"hash":"425311731","position":{"z":33.647915,"y":-1652.960083,"x":-182.354691},"blip_icon":1,"model":"prop_bush_ivy_02_pot"}],"type":"OBJECT","offset":{"z":1.8,"y":0.9,"x":6.8},"rotation_order":2,"options":{"object_tint":0,"is_explosion_proof":false,"lod_distance":16960,"has_collision":true,"is_light_on":true,"is_attached":true,"buoyancy":0.0,"is_bullet_proof":false,"is_mission_entity":true,"use_soft_pinning":true,"is_dynamic":true,"is_fire_proof":false,"gravity":0.0,"is_invincible":true,"alpha":255,"bone_index":0,"weight":0.0,"is_visible":true,"is_networked":true,"is_melee_proof":false,"is_driver_visible":true,"has_gravity":true},"name":"425311731","num_bones":0,"rotation":{"z":90,"y":0,"x":-90},"hash":"425311731","position":{"z":33.643578,"y":-1646.910278,"x":-183.135437},"blip_icon":1,"model":"prop_bush_ivy_02_pot"}],"type":"OBJECT","offset":{"z":1.1,"y":-2.9,"x":0},"rotation_order":2,"options":{"object_tint":0,"is_explosion_proof":false,"lod_distance":16960,"has_collision":true,"is_light_on":true,"is_attached":true,"buoyancy":0.0,"is_bullet_proof":false,"is_mission_entity":true,"use_soft_pinning":true,"is_dynamic":true,"is_fire_proof":false,"gravity":0.0,"is_invincible":true,"alpha":255,"bone_index":0,"weight":0.0,"is_visible":true,"is_networked":true,"is_melee_proof":false,"is_driver_visible":true,"has_gravity":true},"name":"prop_bush_ivy_01_1m","num_bones":0,"rotation":{"z":90,"y":0,"x":-90},"hash":754902525,"position":{"z":34.408951,"y":-1653.415283,"x":-180.417267},"blip_icon":1,"model":"prop_bush_ivy_01_1m"}],"rotation_order":2,"author":"AlexxiDoVa19","rotation":{"z":0,"y":0,"x":0},"version":"Constructor 0.34b10 / 0.34b7 / 0.34b5","blip_icon":1,"blip_sprite":1,"world_rotation":{"z":7.353568,"y":4.360377,"x":-0.04072},"position":{"z":33.310074,"y":-1650.550659,"x":-180.871292},"options":{"object_tint":0,"is_explosion_proof":false,"lod_distance":16960,"has_collision":true,"is_light_on":true,"is_attached":false,"buoyancy":0.0,"is_bullet_proof":false,"is_mission_entity":true,"use_soft_pinning":true,"is_dynamic":true,"is_fire_proof":false,"gravity":0.0,"is_invincible":true,"alpha":255,"bone_index":0,"weight":0.0,"is_visible":true,"is_networked":true,"is_melee_proof":false,"is_driver_visible":true,"has_gravity":true},"type":"VEHICLE","name":"camo tank","num_bones":200,"hash":782665360,"created":"2023-02-18T19:04:06Z","offset":{"z":0,"y":0,"x":0},"model":"RHINO"}